AutoNaviAPI/__init__.py
AutoNaviAPI/main.py
AutoNaviAPI-0.0.2.dist-info/LICENSE.txt
AutoNaviAPI-0.0.2.dist-info/METADATA
AutoNaviAPI-0.0.2.dist-info/WHEEL
AutoNaviAPI-0.0.2.dist-info/top_level.txt
AutoNaviAPI-0.0.2.dist-info/RECORD
