Metadata-Version: 2.1
Name: AutoNaviAPI
Version: 0.0.2
Summary: Use AutoNavi API for map-related operations
Home-page: https://github.com/John-is-playing/AutoNaviAPI
Author: 姬乔恩
Author-email: x297269694@outlook.com
License: UNKNOWN
Platform: UNKNOWN
Classifier: Programming Language :: Python :: 3
Classifier: License :: OSI Approved :: MIT License
Classifier: Operating System :: OS Independent
Requires-Python: >=3.6
License-File: LICENSE.txt
